treeconfigparser/__init__.py
treeconfigparser-1.1.0.dist-info/LICENSE
treeconfigparser-1.1.0.dist-info/METADATA
treeconfigparser-1.1.0.dist-info/WHEEL
treeconfigparser-1.1.0.dist-info/top_level.txt
treeconfigparser-1.1.0.dist-info/RECORD
