Metadata-Version: 2.1
Name: treeconfigparser
Version: 1.1.0
Summary: Custom configuration parser based on a tree
Home-page: https://github.com/cerea-daml/treeconfigparser
Author: Alban Farchi
Author-email: alban.farchi@enpc.fr
License: UNKNOWN
Project-URL: Documentation, https://cerea-daml.github.io/treeconfigparser/
Project-URL: Source, https://github.com/cerea-daml/treeconfigparser
Project-URL: Bug Tracker, https://github.com/cerea-daml/treeconfigparser/issues
Platform: UNKNOWN
Classifier: Intended Audience :: Developers
Classifier: License :: OSI Approved :: MIT License
Classifier: Programming Language :: Python :: 3
Classifier: Programming Language :: Python :: 3 :: Only
Classifier: Operating System :: OS Independent
Requires-Python: >=3.6
Requires-Dist: path
Requires-Dist: numpy
